README.rst
setup.py
cornel_movie_dialogs_corpus_storm.egg-info/PKG-INFO
cornel_movie_dialogs_corpus_storm.egg-info/SOURCES.txt
cornel_movie_dialogs_corpus_storm.egg-info/dependency_links.txt
cornel_movie_dialogs_corpus_storm.egg-info/top_level.txt
mdcorpus/__init__.py
mdcorpus/orm.py
mdcorpus/parser.py
scripts/generate-mdcorpus-database.py