Metadata-Version: 1.0
Name: cornel-movie-dialogs-corpus-storm
Version: 0.1.1
Summary: A set of python modules for cornel movie-dialogs corpus with storm
Home-page: https://github.com/sosuke-k/cornel-movie-dialogs-corpus-storm
Author: Sosuke Kato
Author-email: snoopies.drum@gmail.com
License: MIT
Platform: UNKNOWN
